dike/__init__.py
dike/_batch.py
dike/_limit_jobs.py
dike/_retry.py
dike-1.0.1.dist-info/METADATA
dike-1.0.1.dist-info/WHEEL
dike-1.0.1.dist-info/licenses/LICENSE
dike-1.0.1.dist-info/RECORD
