Metadata-Version: 2.3
Name: dike
Version: 1.0.1
Summary: Python asyncio tools for web service resilience.
Project-URL: Homepage, https://github.com/chr1st1ank/dike
Project-URL: Documentation, https://chr1st1ank.github.io/dike/
Project-URL: Repository, https://github.com/chr1st1ank/dike.git
Project-URL: Issues, https://github.com/chr1st1ank/dike/issues
Author-email: Christian Krudewig <chr1st1ank@krudewig-online.de>
License-Expression: Apache-2.0
License-File: LICENSE
Classifier: Development Status :: 5 - Production/Stable
Classifier: Framework :: AsyncIO
Classifier: Intended Audience :: Developers
Classifier: License :: OSI Approved :: Apache Software License
Classifier: Natural Language :: English
Classifier: Operating System :: OS Independent
Classifier: Programming Language :: Python
Classifier: Programming Language :: Python :: 3
Classifier: Programming Language :: Python :: 3.7
Classifier: Programming Language :: Python :: 3.8
Classifier: Programming Language :: Python :: 3.9
Classifier: Programming Language :: Python :: 3.10
Classifier: Programming Language :: Python :: 3.11
Classifier: Programming Language :: Python :: 3.12
Classifier: Programming Language :: Python :: 3.13
Requires-Python: <4.0,>=3.7.1
Provides-Extra: dev
Requires-Dist: bump2version~=1.0; extra == 'dev'
Requires-Dist: docutils; (python_version == '3.9') and extra == 'dev'
Requires-Dist: fastapi~=0.88; extra == 'dev'
Requires-Dist: httpx~=0.23; extra == 'dev'
Requires-Dist: invoke~=2.0.0; extra == 'dev'
Requires-Dist: mkapi; extra == 'dev'
Requires-Dist: mkdocs-autorefs; extra == 'dev'
Requires-Dist: mkdocs-include-markdown-plugin; extra == 'dev'
Requires-Dist: mkdocs~=1.4; extra == 'dev'
Requires-Dist: numpy; extra == 'dev'
Requires-Dist: phmdoctest~=1.2; extra == 'dev'
Requires-Dist: pre-commit~=2.20; extra == 'dev'
Requires-Dist: pytest-cov; extra == 'dev'
Requires-Dist: pytest-parametrized~=1.4; extra == 'dev'
Requires-Dist: pytest~=7.1; extra == 'dev'
Requires-Dist: toml; extra == 'dev'
Requires-Dist: tox; extra == 'dev'
Requires-Dist: twine; extra == 'dev'
Requires-Dist: uvicorn~=0.20; extra == 'dev'
Requires-Dist: yamllint; extra == 'dev'
Provides-Extra: doc
Requires-Dist: mkapi~=1.0; extra == 'doc'
Requires-Dist: mkdocs-autorefs; extra == 'doc'
Requires-Dist: mkdocs-include-markdown-plugin~=4.0; (python_version == '3.9') and extra == 'doc'
Requires-Dist: mkdocs~=1.4; extra == 'doc'
Requires-Dist: pymdown-extensions~=9.7; extra == 'doc'
Provides-Extra: test
Requires-Dist: phmdoctest; extra == 'test'
Requires-Dist: pytest; extra == 'test'
Requires-Dist: pytest-cov; extra == 'test'
Requires-Dist: xdoctest~=1.1; extra == 'test'
Requires-Dist: yamllint; extra == 'test'
